pycle/__init__.py
pycle/compressive_learning.py
pycle/sketching.py
pycle/third_party.py
pycle/utils.py
pycle-1.2.dist-info/LICENSE
pycle-1.2.dist-info/METADATA
pycle-1.2.dist-info/WHEEL
pycle-1.2.dist-info/top_level.txt
pycle-1.2.dist-info/RECORD
