Metadata-Version: 2.1
Name: pycle
Version: 1.2
Summary: Python toolbox for Compressive Learning (machine learning from a sketch)
Home-page: https://github.com/schellekensv/pycle
Author: Vincent Schellekens
Author-email: vincent.schellekens@uclouvain.be
License: UNKNOWN
Platform: UNKNOWN
Classifier: Programming Language :: Python :: 3
Classifier: License :: OSI Approved :: MIT License
Classifier: Operating System :: OS Independent
Requires-Python: >=3.6
